<?xml version="1.0" encoding="UTF-8"?>
<!DOCTYPE mapper PUBLIC "-//mybatis.org//DTD Mapper 3.0//EN" "http://mybatis.org/dtd/mybatis-3-mapper.dtd">
<mapper namespace="org.dcm4che3.tool.dcmqrscp.mybatis.mapper.DicomcodeMapper">
  <resultMap id="BaseResultMap" type="org.dcm4che3.tool.dcmqrscp.mybatis.entity.Dicomcode">
    <!--
      WARNING - @mbg.generated
      This element is automatically generated by MyBatis Generator, do not modify.
    -->
    <id column="id" jdbcType="INTEGER" property="id" />
    <result column="x00080100" jdbcType="VARCHAR" property="x00080100" />
    <result column="x00080102" jdbcType="VARCHAR" property="x00080102" />
    <result column="x00080103" jdbcType="VARCHAR" property="x00080103" />
    <result column="x00080104" jdbcType="VARCHAR" property="x00080104" />
    <result column="createdAt" jdbcType="TIMESTAMP" property="createdat" />
    <result column="updatedAt" jdbcType="TIMESTAMP" property="updatedat" />
    <result column="SOPInstanceUID" jdbcType="VARCHAR" property="sopinstanceuid" />
    <result column="x0040A088" jdbcType="INTEGER" property="x0040a088" />
    <result column="ConceptNameCodeId" jdbcType="INTEGER" property="conceptnamecodeid" />
    <result column="ConceptCodeId" jdbcType="INTEGER" property="conceptcodeid" />
  </resultMap>
  <sql id="Example_Where_Clause">
    <!--
      WARNING - @mbg.generated
      This element is automatically generated by MyBatis Generator, do not modify.
    -->
    <where>
      <foreach collection="oredCriteria" item="criteria" separator="or">
        <if test="criteria.valid">
          <trim prefix="(" prefixOverrides="and" suffix=")">
            <foreach collection="criteria.criteria" item="criterion">
              <choose>
                <when test="criterion.noValue">
                  and ${criterion.condition}
                </when>
                <when test="criterion.singleValue">
                  and ${criterion.condition} #{criterion.value}
                </when>
                <when test="criterion.betweenValue">
                  and ${criterion.condition} #{criterion.value} and #{criterion.secondValue}
                </when>
                <when test="criterion.listValue">
                  and ${criterion.condition}
                  <foreach close=")" collection="criterion.value" item="listItem" open="(" separator=",">
                    #{listItem}
                  </foreach>
                </when>
              </choose>
            </foreach>
          </trim>
        </if>
      </foreach>
    </where>
  </sql>
  <sql id="Update_By_Example_Where_Clause">
    <!--
      WARNING - @mbg.generated
      This element is automatically generated by MyBatis Generator, do not modify.
    -->
    <where>
      <foreach collection="example.oredCriteria" item="criteria" separator="or">
        <if test="criteria.valid">
          <trim prefix="(" prefixOverrides="and" suffix=")">
            <foreach collection="criteria.criteria" item="criterion">
              <choose>
                <when test="criterion.noValue">
                  and ${criterion.condition}
                </when>
                <when test="criterion.singleValue">
                  and ${criterion.condition} #{criterion.value}
                </when>
                <when test="criterion.betweenValue">
                  and ${criterion.condition} #{criterion.value} and #{criterion.secondValue}
                </when>
                <when test="criterion.listValue">
                  and ${criterion.condition}
                  <foreach close=")" collection="criterion.value" item="listItem" open="(" separator=",">
                    #{listItem}
                  </foreach>
                </when>
              </choose>
            </foreach>
          </trim>
        </if>
      </foreach>
    </where>
  </sql>
  <sql id="Base_Column_List">
    <!--
      WARNING - @mbg.generated
      This element is automatically generated by MyBatis Generator, do not modify.
    -->
    id, x00080100, x00080102, x00080103, x00080104, createdAt, updatedAt, SOPInstanceUID, 
    x0040A088, ConceptNameCodeId, ConceptCodeId
  </sql>
  <select id="selectByExample" parameterType="org.dcm4che3.tool.dcmqrscp.mybatis.entity.DicomcodeExample" resultMap="BaseResultMap">
    <!--
      WARNING - @mbg.generated
      This element is automatically generated by MyBatis Generator, do not modify.
    -->
    select
    <if test="distinct">
      distinct
    </if>
    <include refid="Base_Column_List" />
    from public.DicomCode
    <if test="_parameter != null">
      <include refid="Example_Where_Clause" />
    </if>
    <if test="orderByClause != null">
      order by ${orderByClause}
    </if>
  </select>
  <select id="selectByPrimaryKey" parameterType="java.lang.Integer" resultMap="BaseResultMap">
    <!--
      WARNING - @mbg.generated
      This element is automatically generated by MyBatis Generator, do not modify.
    -->
    select 
    <include refid="Base_Column_List" />
    from public.DicomCode
    where id = #{id,jdbcType=INTEGER}
  </select>
  <delete id="deleteByPrimaryKey" parameterType="java.lang.Integer">
    <!--
      WARNING - @mbg.generated
      This element is automatically generated by MyBatis Generator, do not modify.
    -->
    delete from public.DicomCode
    where id = #{id,jdbcType=INTEGER}
  </delete>
  <delete id="deleteByExample" parameterType="org.dcm4che3.tool.dcmqrscp.mybatis.entity.DicomcodeExample">
    <!--
      WARNING - @mbg.generated
      This element is automatically generated by MyBatis Generator, do not modify.
    -->
    delete from public.DicomCode
    <if test="_parameter != null">
      <include refid="Example_Where_Clause" />
    </if>
  </delete>
  <insert id="insert" parameterType="org.dcm4che3.tool.dcmqrscp.mybatis.entity.Dicomcode">
    <!--
      WARNING - @mbg.generated
      This element is automatically generated by MyBatis Generator, do not modify.
    -->
    insert into public.DicomCode (id, x00080100, x00080102, 
      x00080103, x00080104, createdAt, 
      updatedAt, SOPInstanceUID, x0040A088, 
      ConceptNameCodeId, ConceptCodeId)
    values (#{id,jdbcType=INTEGER}, #{x00080100,jdbcType=VARCHAR}, #{x00080102,jdbcType=VARCHAR}, 
      #{x00080103,jdbcType=VARCHAR}, #{x00080104,jdbcType=VARCHAR}, #{createdat,jdbcType=TIMESTAMP}, 
      #{updatedat,jdbcType=TIMESTAMP}, #{sopinstanceuid,jdbcType=VARCHAR}, #{x0040a088,jdbcType=INTEGER}, 
      #{conceptnamecodeid,jdbcType=INTEGER}, #{conceptcodeid,jdbcType=INTEGER})
  </insert>
  <insert id="insertSelective" parameterType="org.dcm4che3.tool.dcmqrscp.mybatis.entity.Dicomcode">
    <!--
      WARNING - @mbg.generated
      This element is automatically generated by MyBatis Generator, do not modify.
    -->
    insert into public.DicomCode
    <trim prefix="(" suffix=")" suffixOverrides=",">
      <if test="id != null">
        id,
      </if>
      <if test="x00080100 != null">
        x00080100,
      </if>
      <if test="x00080102 != null">
        x00080102,
      </if>
      <if test="x00080103 != null">
        x00080103,
      </if>
      <if test="x00080104 != null">
        x00080104,
      </if>
      <if test="createdat != null">
        createdAt,
      </if>
      <if test="updatedat != null">
        updatedAt,
      </if>
      <if test="sopinstanceuid != null">
        SOPInstanceUID,
      </if>
      <if test="x0040a088 != null">
        x0040A088,
      </if>
      <if test="conceptnamecodeid != null">
        ConceptNameCodeId,
      </if>
      <if test="conceptcodeid != null">
        ConceptCodeId,
      </if>
    </trim>
    <trim prefix="values (" suffix=")" suffixOverrides=",">
      <if test="id != null">
        #{id,jdbcType=INTEGER},
      </if>
      <if test="x00080100 != null">
        #{x00080100,jdbcType=VARCHAR},
      </if>
      <if test="x00080102 != null">
        #{x00080102,jdbcType=VARCHAR},
      </if>
      <if test="x00080103 != null">
        #{x00080103,jdbcType=VARCHAR},
      </if>
      <if test="x00080104 != null">
        #{x00080104,jdbcType=VARCHAR},
      </if>
      <if test="createdat != null">
        #{createdat,jdbcType=TIMESTAMP},
      </if>
      <if test="updatedat != null">
        #{updatedat,jdbcType=TIMESTAMP},
      </if>
      <if test="sopinstanceuid != null">
        #{sopinstanceuid,jdbcType=VARCHAR},
      </if>
      <if test="x0040a088 != null">
        #{x0040a088,jdbcType=INTEGER},
      </if>
      <if test="conceptnamecodeid != null">
        #{conceptnamecodeid,jdbcType=INTEGER},
      </if>
      <if test="conceptcodeid != null">
        #{conceptcodeid,jdbcType=INTEGER},
      </if>
    </trim>
  </insert>
  <select id="countByExample" parameterType="org.dcm4che3.tool.dcmqrscp.mybatis.entity.DicomcodeExample" resultType="java.lang.Long">
    <!--
      WARNING - @mbg.generated
      This element is automatically generated by MyBatis Generator, do not modify.
    -->
    select count(*) from public.DicomCode
    <if test="_parameter != null">
      <include refid="Example_Where_Clause" />
    </if>
  </select>
  <update id="updateByExampleSelective" parameterType="map">
    <!--
      WARNING - @mbg.generated
      This element is automatically generated by MyBatis Generator, do not modify.
    -->
    update public.DicomCode
    <set>
      <if test="record.id != null">
        id = #{record.id,jdbcType=INTEGER},
      </if>
      <if test="record.x00080100 != null">
        x00080100 = #{record.x00080100,jdbcType=VARCHAR},
      </if>
      <if test="record.x00080102 != null">
        x00080102 = #{record.x00080102,jdbcType=VARCHAR},
      </if>
      <if test="record.x00080103 != null">
        x00080103 = #{record.x00080103,jdbcType=VARCHAR},
      </if>
      <if test="record.x00080104 != null">
        x00080104 = #{record.x00080104,jdbcType=VARCHAR},
      </if>
      <if test="record.createdat != null">
        createdAt = #{record.createdat,jdbcType=TIMESTAMP},
      </if>
      <if test="record.updatedat != null">
        updatedAt = #{record.updatedat,jdbcType=TIMESTAMP},
      </if>
      <if test="record.sopinstanceuid != null">
        SOPInstanceUID = #{record.sopinstanceuid,jdbcType=VARCHAR},
      </if>
      <if test="record.x0040a088 != null">
        x0040A088 = #{record.x0040a088,jdbcType=INTEGER},
      </if>
      <if test="record.conceptnamecodeid != null">
        ConceptNameCodeId = #{record.conceptnamecodeid,jdbcType=INTEGER},
      </if>
      <if test="record.conceptcodeid != null">
        ConceptCodeId = #{record.conceptcodeid,jdbcType=INTEGER},
      </if>
    </set>
    <if test="_parameter != null">
      <include refid="Update_By_Example_Where_Clause" />
    </if>
  </update>
  <update id="updateByExample" parameterType="map">
    <!--
      WARNING - @mbg.generated
      This element is automatically generated by MyBatis Generator, do not modify.
    -->
    update public.DicomCode
    set id = #{record.id,jdbcType=INTEGER},
      x00080100 = #{record.x00080100,jdbcType=VARCHAR},
      x00080102 = #{record.x00080102,jdbcType=VARCHAR},
      x00080103 = #{record.x00080103,jdbcType=VARCHAR},
      x00080104 = #{record.x00080104,jdbcType=VARCHAR},
      createdAt = #{record.createdat,jdbcType=TIMESTAMP},
      updatedAt = #{record.updatedat,jdbcType=TIMESTAMP},
      SOPInstanceUID = #{record.sopinstanceuid,jdbcType=VARCHAR},
      x0040A088 = #{record.x0040a088,jdbcType=INTEGER},
      ConceptNameCodeId = #{record.conceptnamecodeid,jdbcType=INTEGER},
      ConceptCodeId = #{record.conceptcodeid,jdbcType=INTEGER}
    <if test="_parameter != null">
      <include refid="Update_By_Example_Where_Clause" />
    </if>
  </update>
  <update id="updateByPrimaryKeySelective" parameterType="org.dcm4che3.tool.dcmqrscp.mybatis.entity.Dicomcode">
    <!--
      WARNING - @mbg.generated
      This element is automatically generated by MyBatis Generator, do not modify.
    -->
    update public.DicomCode
    <set>
      <if test="x00080100 != null">
        x00080100 = #{x00080100,jdbcType=VARCHAR},
      </if>
      <if test="x00080102 != null">
        x00080102 = #{x00080102,jdbcType=VARCHAR},
      </if>
      <if test="x00080103 != null">
        x00080103 = #{x00080103,jdbcType=VARCHAR},
      </if>
      <if test="x00080104 != null">
        x00080104 = #{x00080104,jdbcType=VARCHAR},
      </if>
      <if test="createdat != null">
        createdAt = #{createdat,jdbcType=TIMESTAMP},
      </if>
      <if test="updatedat != null">
        updatedAt = #{updatedat,jdbcType=TIMESTAMP},
      </if>
      <if test="sopinstanceuid != null">
        SOPInstanceUID = #{sopinstanceuid,jdbcType=VARCHAR},
      </if>
      <if test="x0040a088 != null">
        x0040A088 = #{x0040a088,jdbcType=INTEGER},
      </if>
      <if test="conceptnamecodeid != null">
        ConceptNameCodeId = #{conceptnamecodeid,jdbcType=INTEGER},
      </if>
      <if test="conceptcodeid != null">
        ConceptCodeId = #{conceptcodeid,jdbcType=INTEGER},
      </if>
    </set>
    where id = #{id,jdbcType=INTEGER}
  </update>
  <update id="updateByPrimaryKey" parameterType="org.dcm4che3.tool.dcmqrscp.mybatis.entity.Dicomcode">
    <!--
      WARNING - @mbg.generated
      This element is automatically generated by MyBatis Generator, do not modify.
    -->
    update public.DicomCode
    set x00080100 = #{x00080100,jdbcType=VARCHAR},
      x00080102 = #{x00080102,jdbcType=VARCHAR},
      x00080103 = #{x00080103,jdbcType=VARCHAR},
      x00080104 = #{x00080104,jdbcType=VARCHAR},
      createdAt = #{createdat,jdbcType=TIMESTAMP},
      updatedAt = #{updatedat,jdbcType=TIMESTAMP},
      SOPInstanceUID = #{sopinstanceuid,jdbcType=VARCHAR},
      x0040A088 = #{x0040a088,jdbcType=INTEGER},
      ConceptNameCodeId = #{conceptnamecodeid,jdbcType=INTEGER},
      ConceptCodeId = #{conceptcodeid,jdbcType=INTEGER}
    where id = #{id,jdbcType=INTEGER}
  </update>
</mapper>